cbfeeds/__init__.py
cbfeeds/feed.py
cbfeeds-0.8.0.dist-info/DESCRIPTION.rst
cbfeeds-0.8.0.dist-info/METADATA
cbfeeds-0.8.0.dist-info/RECORD
cbfeeds-0.8.0.dist-info/WHEEL
cbfeeds-0.8.0.dist-info/metadata.json
cbfeeds-0.8.0.dist-info/top_level.txt
